{
    "name": "M2S010-MICROSEMI-BD",
    "vendor": "RealThread",
    "description": "M2S010-MICROSEMI-BD Board Support Packages",
    "license": "",
    "repository": "https://github.com/RT-Thread-Studio/sdk-bsp-smartfusion2.git",
    "releases": [
        {
            "version": "1.0.0",
            "date": "2021-02-01",
            "description": "v1.0.0 release",
            "size": "5 MB",
            "url": "https://github.com/RT-Thread-Studio/sdk-bsp-smartfusion2/archive/1.0.0.zip"
        }
    ]
}
